wechat_oa_mcp/__init__.py
wechat_oa_mcp/__main__.py
wechat_oa_mcp/cli.py
wechat_oa_mcp/server.py
iflow_mcp_kakaxi3019_wechat_oa_mcp-0.1.1.dist-info/METADATA
iflow_mcp_kakaxi3019_wechat_oa_mcp-0.1.1.dist-info/WHEEL
iflow_mcp_kakaxi3019_wechat_oa_mcp-0.1.1.dist-info/entry_points.txt
iflow_mcp_kakaxi3019_wechat_oa_mcp-0.1.1.dist-info/top_level.txt
iflow_mcp_kakaxi3019_wechat_oa_mcp-0.1.1.dist-info/RECORD
